spanserver/__init__.py
spanserver/_api.py
spanserver/_method_wrapper.py
spanserver/_openapi.py
spanserver/_req_resp.py
spanserver/_route.py
spanserver/_schema_info.py
spanserver/_version.py
spanserver/test_utils/__init__.py
spanserver/test_utils/_api.py
spanserver/test_utils/_errors.py
spanserver-0.7.2.dist-info/METADATA
spanserver-0.7.2.dist-info/WHEEL
spanserver-0.7.2.dist-info/top_level.txt
spanserver-0.7.2.dist-info/RECORD
